testlwroblewski/__init__.py
testlwroblewski/m_mod_lwroblewski.py
testlwroblewski-0.0.1.dist-info/LICENSE.txt
testlwroblewski-0.0.1.dist-info/METADATA
testlwroblewski-0.0.1.dist-info/WHEEL
testlwroblewski-0.0.1.dist-info/top_level.txt
testlwroblewski-0.0.1.dist-info/RECORD
