Metadata-Version: 2.1
Name: testlwroblewski
Version: 0.0.1
Summary: My test package
Author-email: LW <luki5@o2.pl>
License: MIT License
Keywords: testlwroblewski,name,surname,blabla
Classifier: Framework :: IDLE
Classifier: Natural Language :: Polish
Requires-Python: >=3.0
License-File: LICENSE.txt
Requires-Dist: python-version (>='3.0')
Requires-Dist: numpy
